{"version":2,"kind":"Article","sha256":"24a3d89051a88480df139a89df346ac071dfeef7b896fd527eb2dbae9025e006","slug":"gravity-index","location":"/notebooks/gravity_index.md","dependencies":[],"frontmatter":{"title":"Gravity","content_includes_title":false,"authors":[{"id":"devincowan","nameParsed":{"literal":"Devin Cowan","given":"Devin","family":"Cowan"},"name":"Devin Cowan","orcid":"0000-0002-0089-402X","roles":["Writing – original draft","Writing – review & editing","Software"],"affiliations":["ubc"]},{"id":"lindseyheagy","nameParsed":{"literal":"Lindsey Heagy","given":"Lindsey","family":"Heagy"},"name":"Lindsey Heagy","orcid":"0000-0002-1551-5926","roles":["Supervision","Project administration","Software"],"affiliations":["ubc"]},{"id":"santisoler","nameParsed":{"literal":"Santiago Soler","given":"Santiago","family":"Soler"},"name":"Santiago Soler","orcid":"0000-0001-9202-5317","roles":["Writing – review & editing","Software"],"affiliations":["ubc"]},{"id":"thibautastic","nameParsed":{"literal":"Thibaut Astic","given":"Thibaut","family":"Astic"},"name":"Thibaut Astic","roles":["Writing – original draft"],"affiliations":["kobold"]}],"license":{"content":{"id":"CC-BY-4.0","url":"https://creativecommons.org/licenses/by/4.0/","name":"Creative Commons Attribution 4.0 International","free":true,"CC":true},"code":{"id":"MIT","url":"https://opensource.org/licenses/MIT","name":"MIT License","free":true,"osi":true}},"github":"https://github.com/simpeg/user-tutorials","subject":"SimPEG User Tutorials","keywords":["geophysics","inversions","python","open-source"],"affiliations":[{"id":"ubc","name":"University of British Columbia","department":"Department of Earth, Ocean and Atmospheric Sciences","address":"2020 – 2207 Main Mall","city":"Vancouver","state":"British Columbia","postal_code":"V6T 1Z4","country":"Canada","isni":"0000 0001 2288 9830","ror":"https://ror.org/03rmrcq20","phone":"604 822 2449"},{"id":"kobold","name":"Kobold Metals"}],"source_url":"https://github.com/simpeg/user-tutorials/blob/main/notebooks/gravity_index.md","edit_url":"https://github.com/simpeg/user-tutorials/edit/main/notebooks/gravity_index.md","thumbnail":"/user-tutorials/build/ae6c6ed278992f609070dbcd57643aba.jpeg","exports":[{"format":"md","filename":"gravity_index.md","url":"/user-tutorials/build/gravity_index-bebf3a1734aa80cd43a7bee82c5adce4.md"}]},"mdast":{"type":"root","children":[{"type":"block","children":[{"type":"paragraph","position":{"start":{"line":4,"column":1},"end":{"line":4,"column":1}},"children":[{"type":"text","value":"Gravity anomaly and gravity gradiometry data are simulated using functionality within the ","position":{"start":{"line":4,"column":1},"end":{"line":4,"column":1}},"key":"iSELNKJyRn"},{"type":"inlineCode","value":"SimPEG.potential_fields.gravity","position":{"start":{"line":4,"column":1},"end":{"line":4,"column":1}},"key":"XloavDzm7U"},{"type":"text","value":" module. Here, we provide a multitude of introductory and indermediate level tutorials for forward simulation and inversion of gravity anomaly and gravity gradiometry data. Links to each tutorial can be accessed below or from the left-side menu.","position":{"start":{"line":4,"column":1},"end":{"line":4,"column":1}},"key":"C5XRg61qrf"}],"key":"iw8jaT9EIA"},{"type":"container","kind":"figure","children":[{"type":"image","url":"/user-tutorials/build/ae6c6ed278992f609070dbcd57643aba.jpeg","alt":"Earth’s gravity anomalies (image source)","width":"350px","align":"center","data":{"altTextIsAutoGenerated":true},"key":"S04G87fsPR","urlSource":"https://upload.wikimedia.org/wikipedia/commons/1/14/Gravity_anomalies_on_Earth.jpg"},{"type":"caption","children":[{"type":"paragraph","position":{"start":{"line":10,"column":1},"end":{"line":10,"column":1}},"children":[{"type":"text","value":"Earth’s gravity anomalies (","position":{"start":{"line":10,"column":1},"end":{"line":10,"column":1}},"key":"Es8SDE4gkV"},{"type":"link","url":"https://upload.wikimedia.org/wikipedia/commons/1/14/Gravity_anomalies_on_Earth.jpg","position":{"start":{"line":10,"column":1},"end":{"line":10,"column":1}},"children":[{"type":"text","value":"image source","position":{"start":{"line":10,"column":1},"end":{"line":10,"column":1}},"key":"PchfP6zuEK"}],"urlSource":"https://upload.wikimedia.org/wikipedia/commons/1/14/Gravity_anomalies_on_Earth.jpg","key":"MEadU9WKJ7"},{"type":"text","value":")","position":{"start":{"line":10,"column":1},"end":{"line":10,"column":1}},"key":"DCM9wDhxIb"}],"key":"M58i05jhOb"}],"key":"ggiWNIC9Xn"}],"enumerator":"1","key":"rYDxXK4jVn"},{"type":"heading","depth":2,"position":{"start":{"line":13,"column":1},"end":{"line":13,"column":1}},"children":[{"type":"text","value":"Tutorial Notebooks","position":{"start":{"line":13,"column":1},"end":{"line":13,"column":1}},"key":"JQdgaYhVYs"}],"identifier":"tutorial-notebooks","label":"Tutorial Notebooks","html_id":"tutorial-notebooks","implicit":true,"key":"xYRIV8RW8y"},{"type":"paragraph","position":{"start":{"line":15,"column":1},"end":{"line":16,"column":1}},"children":[{"type":"link","url":"/fwd-gravity-anomaly-3d","position":{"start":{"line":15,"column":1},"end":{"line":15,"column":1}},"children":[{"type":"text","value":"3D Forward Simulation of Gravity Anomaly Data","position":{"start":{"line":15,"column":1},"end":{"line":15,"column":1}},"key":"NsziyJfwNx"}],"urlSource":"03-gravity/fwd_gravity_anomaly_3d","dataUrl":"/fwd-gravity-anomaly-3d.json","internal":true,"protocol":"file","key":"KZZU6Ryzfw"},{"type":"text","value":" ","position":{"start":{"line":15,"column":1},"end":{"line":15,"column":1}},"key":"uDS4g8XZKU"},{"type":"inlineMath","value":"({\\color{green}Introductory}","position":{"start":{"line":15,"column":1},"end":{"line":15,"column":1}},"html":"<span class=\"katex\"><span class=\"katex-mathml\"><math xmlns=\"http://www.w3.org/1998/Math/MathML\"><semantics><mrow><mo stretchy=\"false\">(</mo><mstyle mathcolor=\"green\"><mi>I</mi><mi>n</mi><mi>t</mi><mi>r</mi><mi>o</mi><mi>d</mi><mi>u</mi><mi>c</mi><mi>t</mi><mi>o</mi><mi>r</mi><mi>y</mi></mstyle></mrow><annotation encoding=\"application/x-tex\">({\\color{green}Introductory}</annotation></semantics></math></span><span class=\"katex-html\" aria-hidden=\"true\"><span class=\"base\"><span class=\"strut\" style=\"height:1em;vertical-align:-0.25em;\"></span><span class=\"mopen\">(</span><span class=\"mord\"><span class=\"mord mathnormal\" style=\"margin-right:0.07847em;color:green;\">I</span><span class=\"mord mathnormal\" style=\"color:green;\">n</span><span class=\"mord mathnormal\" style=\"color:green;\">t</span><span class=\"mord mathnormal\" style=\"color:green;\">ro</span><span class=\"mord mathnormal\" style=\"color:green;\">d</span><span class=\"mord mathnormal\" style=\"color:green;\">u</span><span class=\"mord mathnormal\" style=\"color:green;\">c</span><span class=\"mord mathnormal\" style=\"color:green;\">t</span><span class=\"mord mathnormal\" style=\"margin-right:0.03588em;color:green;\">ory</span></span></span></span></span>","key":"yPkdHRx1up"},{"type":"text","value":", ","position":{"start":{"line":15,"column":1},"end":{"line":15,"column":1}},"key":"bYLwwTDw5k"},{"type":"inlineMath","value":"{\\color{green}Lightweight})","position":{"start":{"line":15,"column":1},"end":{"line":15,"column":1}},"html":"<span class=\"katex\"><span class=\"katex-mathml\"><math xmlns=\"http://www.w3.org/1998/Math/MathML\"><semantics><mrow><mstyle mathcolor=\"green\"><mi>L</mi><mi>i</mi><mi>g</mi><mi>h</mi><mi>t</mi><mi>w</mi><mi>e</mi><mi>i</mi><mi>g</mi><mi>h</mi><mi>t</mi></mstyle><mo stretchy=\"false\">)</mo></mrow><annotation encoding=\"application/x-tex\">{\\color{green}Lightweight})</annotation></semantics></math></span><span class=\"katex-html\" aria-hidden=\"true\"><span class=\"base\"><span class=\"strut\" style=\"height:1em;vertical-align:-0.25em;\"></span><span class=\"mord\"><span class=\"mord mathnormal\" style=\"color:green;\">L</span><span class=\"mord mathnormal\" style=\"color:green;\">i</span><span class=\"mord mathnormal\" style=\"margin-right:0.03588em;color:green;\">g</span><span class=\"mord mathnormal\" style=\"color:green;\">h</span><span class=\"mord mathnormal\" style=\"margin-right:0.02691em;color:green;\">tw</span><span class=\"mord mathnormal\" style=\"color:green;\">e</span><span class=\"mord mathnormal\" style=\"color:green;\">i</span><span class=\"mord mathnormal\" style=\"margin-right:0.03588em;color:green;\">g</span><span class=\"mord mathnormal\" style=\"color:green;\">h</span><span class=\"mord mathnormal\" style=\"color:green;\">t</span></span><span class=\"mclose\">)</span></span></span></span>","key":"coUOQAIv6D"},{"type":"text","value":"\n","position":{"start":{"line":15,"column":1},"end":{"line":15,"column":1}},"key":"bsGT4HMif6"},{"type":"break","key":"UnzIuz99le"}],"key":"na4LUZ3Jz3"},{"type":"paragraph","position":{"start":{"line":18,"column":1},"end":{"line":19,"column":1}},"children":[{"type":"link","url":"/fwd-gravity-gradiometry-3d","position":{"start":{"line":18,"column":1},"end":{"line":18,"column":1}},"children":[{"type":"text","value":"3D Forward Simulation of Gravity Gradiometry Data","position":{"start":{"line":18,"column":1},"end":{"line":18,"column":1}},"key":"dv4cko3eTQ"}],"urlSource":"03-gravity/fwd_gravity_gradiometry_3d","dataUrl":"/fwd-gravity-gradiometry-3d.json","internal":true,"protocol":"file","key":"rTwNI7qCSm"},{"type":"text","value":" ","position":{"start":{"line":18,"column":1},"end":{"line":18,"column":1}},"key":"PhnONyR9VG"},{"type":"inlineMath","value":"({\\color{green}Introductory}","position":{"start":{"line":18,"column":1},"end":{"line":18,"column":1}},"html":"<span class=\"katex\"><span class=\"katex-mathml\"><math xmlns=\"http://www.w3.org/1998/Math/MathML\"><semantics><mrow><mo stretchy=\"false\">(</mo><mstyle mathcolor=\"green\"><mi>I</mi><mi>n</mi><mi>t</mi><mi>r</mi><mi>o</mi><mi>d</mi><mi>u</mi><mi>c</mi><mi>t</mi><mi>o</mi><mi>r</mi><mi>y</mi></mstyle></mrow><annotation encoding=\"application/x-tex\">({\\color{green}Introductory}</annotation></semantics></math></span><span class=\"katex-html\" aria-hidden=\"true\"><span class=\"base\"><span class=\"strut\" style=\"height:1em;vertical-align:-0.25em;\"></span><span class=\"mopen\">(</span><span class=\"mord\"><span class=\"mord mathnormal\" style=\"margin-right:0.07847em;color:green;\">I</span><span class=\"mord mathnormal\" style=\"color:green;\">n</span><span class=\"mord mathnormal\" style=\"color:green;\">t</span><span class=\"mord mathnormal\" style=\"color:green;\">ro</span><span class=\"mord mathnormal\" style=\"color:green;\">d</span><span class=\"mord mathnormal\" style=\"color:green;\">u</span><span class=\"mord mathnormal\" style=\"color:green;\">c</span><span class=\"mord mathnormal\" style=\"color:green;\">t</span><span class=\"mord mathnormal\" style=\"margin-right:0.03588em;color:green;\">ory</span></span></span></span></span>","key":"Byk6Ytuhjc"},{"type":"text","value":", ","position":{"start":{"line":18,"column":1},"end":{"line":18,"column":1}},"key":"bPifU6JBW9"},{"type":"inlineMath","value":"{\\color{green}Lightweight})","position":{"start":{"line":18,"column":1},"end":{"line":18,"column":1}},"html":"<span class=\"katex\"><span class=\"katex-mathml\"><math xmlns=\"http://www.w3.org/1998/Math/MathML\"><semantics><mrow><mstyle mathcolor=\"green\"><mi>L</mi><mi>i</mi><mi>g</mi><mi>h</mi><mi>t</mi><mi>w</mi><mi>e</mi><mi>i</mi><mi>g</mi><mi>h</mi><mi>t</mi></mstyle><mo stretchy=\"false\">)</mo></mrow><annotation encoding=\"application/x-tex\">{\\color{green}Lightweight})</annotation></semantics></math></span><span class=\"katex-html\" aria-hidden=\"true\"><span class=\"base\"><span class=\"strut\" style=\"height:1em;vertical-align:-0.25em;\"></span><span class=\"mord\"><span class=\"mord mathnormal\" style=\"color:green;\">L</span><span class=\"mord mathnormal\" style=\"color:green;\">i</span><span class=\"mord mathnormal\" style=\"margin-right:0.03588em;color:green;\">g</span><span class=\"mord mathnormal\" style=\"color:green;\">h</span><span class=\"mord mathnormal\" style=\"margin-right:0.02691em;color:green;\">tw</span><span class=\"mord mathnormal\" style=\"color:green;\">e</span><span class=\"mord mathnormal\" style=\"color:green;\">i</span><span class=\"mord mathnormal\" style=\"margin-right:0.03588em;color:green;\">g</span><span class=\"mord mathnormal\" style=\"color:green;\">h</span><span class=\"mord mathnormal\" style=\"color:green;\">t</span></span><span class=\"mclose\">)</span></span></span></span>","key":"vmpN6d2Erl"},{"type":"text","value":"\n","position":{"start":{"line":18,"column":1},"end":{"line":18,"column":1}},"key":"YWO6sRvS60"},{"type":"break","key":"wUSaslkSRE"}],"key":"RithdZ3q74"},{"type":"paragraph","position":{"start":{"line":21,"column":1},"end":{"line":22,"column":1}},"children":[{"type":"link","url":"/inv-gravity-anomaly-3d","position":{"start":{"line":21,"column":1},"end":{"line":21,"column":1}},"children":[{"type":"text","value":"3D Inversion of Gravity Anomaly Data","position":{"start":{"line":21,"column":1},"end":{"line":21,"column":1}},"key":"q99mRcA8NH"}],"urlSource":"03-gravity/inv_gravity_anomaly_3d","dataUrl":"/inv-gravity-anomaly-3d.json","internal":true,"protocol":"file","key":"jjsRf7jHoA"},{"type":"text","value":" ","position":{"start":{"line":21,"column":1},"end":{"line":21,"column":1}},"key":"QVr8QlxQ4v"},{"type":"inlineMath","value":"({\\color{orange}Intermediate}","position":{"start":{"line":21,"column":1},"end":{"line":21,"column":1}},"html":"<span class=\"katex\"><span class=\"katex-mathml\"><math xmlns=\"http://www.w3.org/1998/Math/MathML\"><semantics><mrow><mo stretchy=\"false\">(</mo><mstyle mathcolor=\"orange\"><mi>I</mi><mi>n</mi><mi>t</mi><mi>e</mi><mi>r</mi><mi>m</mi><mi>e</mi><mi>d</mi><mi>i</mi><mi>a</mi><mi>t</mi><mi>e</mi></mstyle></mrow><annotation encoding=\"application/x-tex\">({\\color{orange}Intermediate}</annotation></semantics></math></span><span class=\"katex-html\" aria-hidden=\"true\"><span class=\"base\"><span class=\"strut\" style=\"height:1em;vertical-align:-0.25em;\"></span><span class=\"mopen\">(</span><span class=\"mord\"><span class=\"mord mathnormal\" style=\"margin-right:0.07847em;color:orange;\">I</span><span class=\"mord mathnormal\" style=\"color:orange;\">n</span><span class=\"mord mathnormal\" style=\"color:orange;\">t</span><span class=\"mord mathnormal\" style=\"margin-right:0.02778em;color:orange;\">er</span><span class=\"mord mathnormal\" style=\"color:orange;\">m</span><span class=\"mord mathnormal\" style=\"color:orange;\">e</span><span class=\"mord mathnormal\" style=\"color:orange;\">d</span><span class=\"mord mathnormal\" style=\"color:orange;\">ia</span><span class=\"mord mathnormal\" style=\"color:orange;\">t</span><span class=\"mord mathnormal\" style=\"color:orange;\">e</span></span></span></span></span>","key":"GhHopvwLW4"},{"type":"text","value":", ","position":{"start":{"line":21,"column":1},"end":{"line":21,"column":1}},"key":"GQMiA7Anm9"},{"type":"inlineMath","value":"{\\color{green}Lightweight})","position":{"start":{"line":21,"column":1},"end":{"line":21,"column":1}},"html":"<span class=\"katex\"><span class=\"katex-mathml\"><math xmlns=\"http://www.w3.org/1998/Math/MathML\"><semantics><mrow><mstyle mathcolor=\"green\"><mi>L</mi><mi>i</mi><mi>g</mi><mi>h</mi><mi>t</mi><mi>w</mi><mi>e</mi><mi>i</mi><mi>g</mi><mi>h</mi><mi>t</mi></mstyle><mo stretchy=\"false\">)</mo></mrow><annotation encoding=\"application/x-tex\">{\\color{green}Lightweight})</annotation></semantics></math></span><span class=\"katex-html\" aria-hidden=\"true\"><span class=\"base\"><span class=\"strut\" style=\"height:1em;vertical-align:-0.25em;\"></span><span class=\"mord\"><span class=\"mord mathnormal\" style=\"color:green;\">L</span><span class=\"mord mathnormal\" style=\"color:green;\">i</span><span class=\"mord mathnormal\" style=\"margin-right:0.03588em;color:green;\">g</span><span class=\"mord mathnormal\" style=\"color:green;\">h</span><span class=\"mord mathnormal\" style=\"margin-right:0.02691em;color:green;\">tw</span><span class=\"mord mathnormal\" style=\"color:green;\">e</span><span class=\"mord mathnormal\" style=\"color:green;\">i</span><span class=\"mord mathnormal\" style=\"margin-right:0.03588em;color:green;\">g</span><span class=\"mord mathnormal\" style=\"color:green;\">h</span><span class=\"mord mathnormal\" style=\"color:green;\">t</span></span><span class=\"mclose\">)</span></span></span></span>","key":"xXaI1ivAxt"},{"type":"text","value":"\n","position":{"start":{"line":21,"column":1},"end":{"line":21,"column":1}},"key":"qb4Hm6iuEH"},{"type":"break","key":"S8Ik4hW9Md"}],"key":"nzOSQqWFdH"},{"type":"paragraph","position":{"start":{"line":24,"column":1},"end":{"line":25,"column":1}},"children":[{"type":"link","url":"/weighting-strategies","position":{"start":{"line":24,"column":1},"end":{"line":24,"column":1}},"children":[{"type":"text","value":"Compare weighting strategy with Inversion of surface Gravity Anomaly Data","position":{"start":{"line":24,"column":1},"end":{"line":24,"column":1}},"key":"cCbt8FrP5G"}],"urlSource":"03-gravity/weighting_strategies","dataUrl":"/weighting-strategies.json","internal":true,"protocol":"file","key":"K0xbJD3ijL"},{"type":"text","value":" ","position":{"start":{"line":24,"column":1},"end":{"line":24,"column":1}},"key":"gVaSiLnlJn"},{"type":"inlineMath","value":"({\\color{orange}Intermediate}","position":{"start":{"line":24,"column":1},"end":{"line":24,"column":1}},"html":"<span class=\"katex\"><span class=\"katex-mathml\"><math xmlns=\"http://www.w3.org/1998/Math/MathML\"><semantics><mrow><mo stretchy=\"false\">(</mo><mstyle mathcolor=\"orange\"><mi>I</mi><mi>n</mi><mi>t</mi><mi>e</mi><mi>r</mi><mi>m</mi><mi>e</mi><mi>d</mi><mi>i</mi><mi>a</mi><mi>t</mi><mi>e</mi></mstyle></mrow><annotation encoding=\"application/x-tex\">({\\color{orange}Intermediate}</annotation></semantics></math></span><span class=\"katex-html\" aria-hidden=\"true\"><span class=\"base\"><span class=\"strut\" style=\"height:1em;vertical-align:-0.25em;\"></span><span class=\"mopen\">(</span><span class=\"mord\"><span class=\"mord mathnormal\" style=\"margin-right:0.07847em;color:orange;\">I</span><span class=\"mord mathnormal\" style=\"color:orange;\">n</span><span class=\"mord mathnormal\" style=\"color:orange;\">t</span><span class=\"mord mathnormal\" style=\"margin-right:0.02778em;color:orange;\">er</span><span class=\"mord mathnormal\" style=\"color:orange;\">m</span><span class=\"mord mathnormal\" style=\"color:orange;\">e</span><span class=\"mord mathnormal\" style=\"color:orange;\">d</span><span class=\"mord mathnormal\" style=\"color:orange;\">ia</span><span class=\"mord mathnormal\" style=\"color:orange;\">t</span><span class=\"mord mathnormal\" style=\"color:orange;\">e</span></span></span></span></span>","key":"tsljV3pJSs"},{"type":"text","value":", ","position":{"start":{"line":24,"column":1},"end":{"line":24,"column":1}},"key":"dGxqHYlcCX"},{"type":"inlineMath","value":"{\\color{green}Lightweight})","position":{"start":{"line":24,"column":1},"end":{"line":24,"column":1}},"html":"<span class=\"katex\"><span class=\"katex-mathml\"><math xmlns=\"http://www.w3.org/1998/Math/MathML\"><semantics><mrow><mstyle mathcolor=\"green\"><mi>L</mi><mi>i</mi><mi>g</mi><mi>h</mi><mi>t</mi><mi>w</mi><mi>e</mi><mi>i</mi><mi>g</mi><mi>h</mi><mi>t</mi></mstyle><mo stretchy=\"false\">)</mo></mrow><annotation encoding=\"application/x-tex\">{\\color{green}Lightweight})</annotation></semantics></math></span><span class=\"katex-html\" aria-hidden=\"true\"><span class=\"base\"><span class=\"strut\" style=\"height:1em;vertical-align:-0.25em;\"></span><span class=\"mord\"><span class=\"mord mathnormal\" style=\"color:green;\">L</span><span class=\"mord mathnormal\" style=\"color:green;\">i</span><span class=\"mord mathnormal\" style=\"margin-right:0.03588em;color:green;\">g</span><span class=\"mord mathnormal\" style=\"color:green;\">h</span><span class=\"mord mathnormal\" style=\"margin-right:0.02691em;color:green;\">tw</span><span class=\"mord mathnormal\" style=\"color:green;\">e</span><span class=\"mord mathnormal\" style=\"color:green;\">i</span><span class=\"mord mathnormal\" style=\"margin-right:0.03588em;color:green;\">g</span><span class=\"mord mathnormal\" style=\"color:green;\">h</span><span class=\"mord mathnormal\" style=\"color:green;\">t</span></span><span class=\"mclose\">)</span></span></span></span>","key":"HvKTmeEdTJ"},{"type":"text","value":"\n","position":{"start":{"line":24,"column":1},"end":{"line":24,"column":1}},"key":"ggsZg5TBHI"},{"type":"break","key":"o1HPHD52Gd"}],"key":"jutU7Z5eJ5"}],"key":"mwfg6SOlA3"}],"key":"T5299dxHxi"},"references":{"cite":{"order":[],"data":{}}},"footer":{"navigation":{"prev":{"title":"SimPEG User Tutorials","url":"/","group":"SimPEG User Tutorials"},"next":{"title":"3D Forward Simulation of Gravity Anomaly Data","url":"/fwd-gravity-anomaly-3d","group":"SimPEG User Tutorials"}}},"domain":"http://localhost:3000"}